djira/__init__.py
djira/api.py
djira/app.py
djira/client.py
djira/common.py
djira/ep_registry.py
djira/hookspec.py
djira/plugin_loader.py
djira/schema.py
djira/test_settings.py
djira/test_urls.py
djira/urls.py
djira/validators.py
djira/views.py
djira/endpoints/__init__.py
djira/endpoints/apps.py
djira/endpoints/demo.py
djira/endpoints/system.py
djira/endpoints/urls.py
djira/tests/__init__.py
djira/tests/test_schema.py
djira/tests/test_validators.py
djira/tests/factories/__init__.py
djira-0.2.1.dist-info/METADATA
djira-0.2.1.dist-info/RECORD
djira-0.2.1.dist-info/WHEEL
djira-0.2.1.dist-info/namespace_packages.txt
djira-0.2.1.dist-info/top_level.txt
